django_app_base/__init__.py
django_app_base/admin.py
django_app_base/apps.py
django_app_base/custom_settings.py
django_app_base/list_filter.py
django_app_base/settings.py
django_app_base/settings_items.py
django_app_base/urls.py
django_app_base/__pycache__/__init__.cpython-36.pyc
django_app_base/__pycache__/admin.cpython-36.pyc
django_app_base/__pycache__/settings_items.cpython-36.pyc
django_app_base/backends/AppBackend.py
django_app_base/backends/TokenAuthentication.py
django_app_base/backends/__init__.py
django_app_base/backends/__pycache__/AppBackend.cpython-36.pyc
django_app_base/backends/__pycache__/TokenAuthentication.cpython-36.pyc
django_app_base/backends/__pycache__/__init__.cpython-36.pyc
django_app_base/common/__init__.py
django_app_base/common/http.py
django_app_base/common/__pycache__/__init__.cpython-36.pyc
django_app_base/common/__pycache__/http.cpython-36.pyc
django_app_base/drf/__init__.py
django_app_base/drf/common_import.py
django_app_base/drf/mixin.py
django_app_base/drf/pagination.py
django_app_base/drf/view.py
django_app_base/drf/__pycache__/__init__.cpython-36.pyc
django_app_base/middleware/__init__.py
django_app_base/middleware/authentication.py
django_app_base/middleware/clear_session_middleware.py
django_app_base/middleware/common.py
django_app_base/middleware/local.py
django_app_base/middleware/must_login.py
django_app_base/middleware/permit_user_middleware.py
django_app_base/middleware/__pycache__/__init__.cpython-36.pyc
django_app_base/middleware/__pycache__/authentication.cpython-36.pyc
django_app_base/middleware/__pycache__/common.cpython-36.pyc
django_app_base/middleware/__pycache__/local.cpython-36.pyc
django_app_base/middleware/__pycache__/must_login.cpython-36.pyc
django_app_base/middleware/__pycache__/permit_user_middleware.cpython-36.pyc
django_app_base/models/__init__.py
django_app_base/models/base.py
django_app_base/models/department.py
django_app_base/models/user.py
django_app_base/models/__pycache__/__init__.cpython-36.pyc
django_app_base-0.0.1.dist-info/LICENSE
django_app_base-0.0.1.dist-info/METADATA
django_app_base-0.0.1.dist-info/WHEEL
django_app_base-0.0.1.dist-info/top_level.txt
django_app_base-0.0.1.dist-info/RECORD
